[
    {
        "appliedCrowdControlPerMinute": 0.0,
        "blockPerMinute": 87.5132275132275,
        "cleansesInPerMinute": 42.82186948853615,
        "deathPerMinute": 0.033112582781456956,
        "deathRatio": 5.882352941176471,
        "downPerMinute": 0.2317880794701987,
        "durationInCombat": 1701,
        "evadePerMinute": 37.70723104056437,
        "id": "浩雨林.2014",
        "invulnsPerMinute": 26.20811287477954,
        "opScore": 0.0,
        "profession": "时空",
        "quicknessPerSecond": 0.3448025867136978,
        "regenerationUptime": 88.6815,
        "resPerMinute": 1.5520282186948853,
        "resistancePerSecond": 0.20788330393885948,
        "ripsInPerMinute": 1.4109347442680775,
        "riteUptime": 27.5909,
        "score": 87.08174940594611,
        "stabilityPerSecond": 2.9135743680188124,
        "surviveRatio": 93.87417218543047
    },
    {
        "appliedCrowdControlPerMinute": 0.0,
        "blockPerMinute": 59.25333333333333,
        "cleansesInPerMinute": 35.626666666666665,
        "deathPerMinute": 0.1380368098159509,
        "deathRatio": 25.0,
        "downPerMinute": 0.2760736196319018,
        "durationInCombat": 1125,
        "evadePerMinute": 52.96,
        "id": "小茶籽.3289",
        "invulnsPerMinute": 45.333333333333336,
        "opScore": 0.0,
        "profession": "时空",
        "quicknessPerSecond": 0.3700147555555555,
        "regenerationUptime": 88.6389,
        "resPerMinute": 0.96,
        "resistancePerSecond": 0.25703253333333337,
        "ripsInPerMinute": 0.4266666666666667,
        "riteUptime": 41.2626,
        "score": 83.43480632583504,
        "stabilityPerSecond": 3.653622222222222,
        "surviveRatio": 86.27300613496932
    },
    {
        "appliedCrowdControlPerMinute": 0.0,
        "blockPerMinute": 112.46356696738377,
        "cleansesInPerMinute": 48.21651630811937,
        "deathPerMinute": 0.19867549668874174,
        "deathRatio": 35.294117647058826,
        "downPerMinute": 0.3642384105960265,
        "durationInCombat": 1441,
        "evadePerMinute": 55.62803608605135,
        "id": "西北风刮.1037",
        "invulnsPerMinute": 93.1852879944483,
        "opScore": 0.0,
        "profession": "时空",
        "quicknessPerSecond": 0.40378029146426087,
        "regenerationUptime": 78.5566,
        "resPerMinute": 1.1658570437196392,
        "resistancePerSecond": 0.2367256766134628,
        "ripsInPerMinute": 0.7078417765440667,
        "riteUptime": 31.2319,
        "score": 83.32131946327436,
        "stabilityPerSecond": 4.108286606523247,
        "surviveRatio": 79.52538631346579
    },
    {
        "appliedCrowdControlPerMinute": 0.07159904534606205,
        "blockPerMinute": 67.01670644391407,
        "cleansesInPerMinute": 15.178997613365155,
        "deathPerMinute": 0.06622516556291391,
        "deathRatio": 11.764705882352942,
        "downPerMinute": 0.26490066225165565,
        "durationInCombat": 1676,
        "evadePerMinute": 50.22673031026253,
        "id": "巴萨战场的新希望.2056",
        "invulnsPerMinute": 44.17661097852029,
        "opScore": 0.0,
        "profession": "时空",
        "quicknessPerSecond": 0.39207231503579953,
        "regenerationUptime": 89.615,
        "resPerMinute": 0.4295942720763723,
        "resistancePerSecond": 0.24100375894988071,
        "ripsInPerMinute": 1.5393794749403342,
        "riteUptime": 33.0866,
        "score": 82.15103596021223,
        "stabilityPerSecond": 3.5548687350835326,
        "surviveRatio": 92.49448123620309
    },
    {
        "appliedCrowdControlPerMinute": 0.0,
        "blockPerMinute": 27.759493670886076,
        "cleansesInPerMinute": 4.443037974683545,
        "deathPerMinute": 0.13245033112582782,
        "deathRatio": 23.529411764705884,
        "downPerMinute": 0.2317880794701987,
        "durationInCombat": 1580,
        "evadePerMinute": 145.13924050632912,
        "id": "yokie.9781",
        "pin":true,
        "invulnsPerMinute": 30.949367088607595,
        "opScore": 0.0,
        "profession": "时空",
        "quicknessPerSecond": 0.10450867088607595,
        "regenerationUptime": 89.7073,
        "resPerMinute": 0.4936708860759494,
        "resistancePerSecond": 0.06980386075949367,
        "ripsInPerMinute": 10.367088607594937,
        "riteUptime": 41.8856,
        "score": 50.163154036381925,
        "stabilityPerSecond": 0.89265,
        "surviveRatio": 87.19646799116998
    },
    {
        "appliedCrowdControlPerMinute": 0.6874602164226608,
        "blockPerMinute": 114.80585614258435,
        "cleansesInPerMinute": 73.82558879694461,
        "deathPerMinute": 0.09933774834437087,
        "deathRatio": 17.647058823529413,
        "downPerMinute": 0.16556291390728478,
        "durationInCombat": 1571,
        "evadePerMinute": 34.907702100572884,
        "id": "随便玩玩.8537",
        "invulnsPerMinute": 145.9325270528326,
        "opScore": 0.0,
        "profession": "诗人",
        "quicknessPerSecond": 0.08594379376193506,
        "regenerationUptime": 87.5709,
        "resPerMinute": 0.03819223424570337,
        "resistancePerSecond": 0.057351877784850396,
        "ripsInPerMinute": 1.222151495862508,
        "riteUptime": 40.2184,
        "score": 92.67467313180536,
        "stabilityPerSecond": 3.310058561425843,
        "surviveRatio": 86.69977924944813
    },
    {
        "appliedCrowdControlPerMinute": 0.8879492600422833,
        "blockPerMinute": 57.33615221987315,
        "cleansesInPerMinute": 68.62579281183932,
        "deathPerMinute": 0.11811023622047244,
        "deathRatio": 20.0,
        "downPerMinute": 0.23622047244094488,
        "durationInCombat": 473,
        "evadePerMinute": 32.346723044397464,
        "id": "小茶籽.3289",
        "invulnsPerMinute": 90.5708245243129,
        "opScore": 0.0,
        "profession": "诗人",
        "quicknessPerSecond": 0.09150782241014799,
        "regenerationUptime": 88.6389,
        "resPerMinute": 0.38054968287526425,
        "resistancePerSecond": 0.09437441860465116,
        "ripsInPerMinute": 1.014799154334038,
        "riteUptime": 41.2626,
        "score": 89.46061027783789,
        "stabilityPerSecond": 3.5652600422832985,
        "surviveRatio": 93.11023622047244
    },
    {
        "appliedCrowdControlPerMinute": 0.081799591002045,
        "blockPerMinute": 117.34151329243355,
        "cleansesInPerMinute": 34.23312883435583,
        "deathPerMinute": 0.16556291390728478,
        "deathRatio": 29.41176470588235,
        "downPerMinute": 0.2980132450331126,
        "durationInCombat": 1467,
        "evadePerMinute": 133.90593047034764,
        "id": "stan.1435",
        "invulnsPerMinute": 120.28629856850716,
        "opScore": 0.0,
        "profession": "诗人",
        "quicknessPerSecond": 0.09354444444444444,
        "regenerationUptime": 87.2973,
        "resPerMinute": 0.899795501022495,
        "resistancePerSecond": 0.09015248807089299,
        "ripsInPerMinute": 1.1042944785276074,
        "riteUptime": 25.1549,
        "score": 83.46221389329035,
        "stabilityPerSecond": 3.0864451261077033,
        "surviveRatio": 80.96026490066225
    },
    {
        "appliedCrowdControlPerMinute": 0.3460706560922855,
        "blockPerMinute": 78.64455659697188,
        "cleansesInPerMinute": 61.60057678442682,
        "deathPerMinute": 0.13986013986013984,
        "deathRatio": 25.0,
        "downPerMinute": 0.3846153846153846,
        "durationInCombat": 1387,
        "evadePerMinute": 45.89762076423936,
        "id": "Suver.3791",
        "invulnsPerMinute": 186.87815428983416,
        "opScore": 0.0,
        "profession": "诗人",
        "quicknessPerSecond": 0.08043994232155731,
        "regenerationUptime": 85.51,
        "resPerMinute": 0.08651766402307137,
        "resistancePerSecond": 0.026669646719538573,
        "ripsInPerMinute": 2.379235760634463,
        "riteUptime": 25.7446,
        "score": 82.6549832695543,
        "stabilityPerSecond": 2.8526402307137704,
        "surviveRatio": 80.82750582750583
    },
    {
        "appliedCrowdControlPerMinute": 0.5379557680812911,
        "blockPerMinute": 70.83084279737,
        "cleansesInPerMinute": 58.4578601315003,
        "deathPerMinute": 0.09933774834437087,
        "deathRatio": 17.647058823529413,
        "downPerMinute": 0.26490066225165565,
        "durationInCombat": 1673,
        "evadePerMinute": 24.638374178123133,
        "id": "大灰狼.2538",
        "invulnsPerMinute": 91.34488942020323,
        "opScore": 0.0,
        "profession": "诗人",
        "quicknessPerSecond": 0.07999390316796175,
        "regenerationUptime": 82.4154,
        "resPerMinute": 0.2869097429766886,
        "resistancePerSecond": 0.04551081888822474,
        "ripsInPerMinute": 1.972504482964734,
        "riteUptime": 25.5486,
        "score": 82.13515701262355,
        "stabilityPerSecond": 2.098276748356246,
        "surviveRatio": 92.3289183222958
    },
    {
        "appliedCrowdControlPerMinute": 0.7780320366132722,
        "blockPerMinute": 92.44851258581235,
        "cleansesInPerMinute": 62.05949656750572,
        "deathPerMinute": 0.2980132450331126,
        "deathRatio": 52.94117647058823,
        "downPerMinute": 0.5298013245033113,
        "durationInCombat": 1311,
        "evadePerMinute": 45.81235697940503,
        "id": "张的傀儡.8649",
        "invulnsPerMinute": 145.12585812356977,
        "opScore": 0.0,
        "profession": "诗人",
        "quicknessPerSecond": 0.07611632341723874,
        "regenerationUptime": 75.595,
        "resPerMinute": 0.09153318077803203,
        "resistancePerSecond": 0.03856819221967963,
        "ripsInPerMinute": 0.9610983981693363,
        "riteUptime": 33.4623,
        "score": 76.54316059728936,
        "stabilityPerSecond": 2.839409610983982,
        "surviveRatio": 72.35099337748345
    },
    {
        "appliedCrowdControlPerMinute": 0.6260032102728732,
        "blockPerMinute": 126.74157303370787,
        "cleansesInPerMinute": 60.77046548956662,
        "deathPerMinute": 0.2980132450331126,
        "deathRatio": 52.94117647058823,
        "downPerMinute": 0.5960264900662252,
        "durationInCombat": 1246,
        "evadePerMinute": 95.68218298555378,
        "id": "Grace.1625",
        "invulnsPerMinute": 184.95987158908508,
        "opScore": 0.0,
        "profession": "诗人",
        "quicknessPerSecond": 0.09662728731942215,
        "regenerationUptime": 79.4467,
        "resPerMinute": 0.33707865168539325,
        "resistancePerSecond": 0.05717199036918138,
        "ripsInPerMinute": 1.8298555377207064,
        "riteUptime": 27.0978,
        "score": 75.9903047633221,
        "stabilityPerSecond": 3.5612784911717497,
        "surviveRatio": 68.76379690949227
    },
    {
        "appliedCrowdControlPerMinute": 0.27507163323782235,
        "blockPerMinute": 5.948424068767909,
        "cleansesInPerMinute": 68.87106017191978,
        "deathPerMinute": 0.0,
        "deathRatio": 0.0,
        "downPerMinute": 0.0,
        "durationInCombat": 1745,
        "evadePerMinute": 37.13467048710602,
        "id": "kssws.2315",
        "invulnsPerMinute": 3.507163323782235,
        "opScore": 0.0,
        "profession": "圣言",
        "quicknessPerSecond": 0.5206955300859598,
        "regenerationUptime": 92.1281,
        "resPerMinute": 0.7908309455587393,
        "resistancePerSecond": 0.42004320916905447,
        "ripsInPerMinute": 0.034383954154727794,
        "riteUptime": 40.2984,
        "score": 98.95415472779369,
        "stabilityPerSecond": 1.3338641833810887,
        "surviveRatio": 96.30242825607064
    },
    {
        "appliedCrowdControlPerMinute": 0.7490636704119851,
        "blockPerMinute": 7.865168539325843,
        "cleansesInPerMinute": 67.71535580524345,
        "deathPerMinute": 0.06622516556291391,
        "deathRatio": 11.764705882352942,
        "downPerMinute": 0.13245033112582782,
        "durationInCombat": 1602,
        "evadePerMinute": 28.426966292134832,
        "id": "Ajas.5439",
        "invulnsPerMinute": 11.535580524344569,
        "opScore": 0.0,
        "profession": "圣言",
        "quicknessPerSecond": 0.5841041822721599,
        "regenerationUptime": 90.1212,
        "resPerMinute": 0.6741573033707865,
        "resistancePerSecond": 0.3858222222222222,
        "ripsInPerMinute": 0.03745318352059925,
        "riteUptime": 36.7379,
        "score": 92.54110660515416,
        "stabilityPerSecond": 1.4113102372034958,
        "surviveRatio": 88.41059602649007
    },
    {
        "appliedCrowdControlPerMinute": 0.638697557921102,
        "blockPerMinute": 6.161552911709455,
        "cleansesInPerMinute": 73.6380713838447,
        "deathPerMinute": 0.06622516556291391,
        "deathRatio": 11.764705882352942,
        "downPerMinute": 0.16556291390728478,
        "durationInCombat": 1597,
        "evadePerMinute": 41.252348152786475,
        "id": "kilig.3819",
        "invulnsPerMinute": 9.505322479649342,
        "opScore": 0.0,
        "profession": "圣言",
        "quicknessPerSecond": 0.49463700688791473,
        "regenerationUptime": 93.7214,
        "resPerMinute": 0.8265497808390733,
        "resistancePerSecond": 0.5254959924859112,
        "ripsInPerMinute": 0.11271133375078271,
        "riteUptime": 27.8262,
        "score": 92.51023234790398,
        "stabilityPerSecond": 1.360408891671885,
        "surviveRatio": 88.13465783664459
    },
    {
        "appliedCrowdControlPerMinute": 0.23121387283236994,
        "blockPerMinute": 9.710982658959537,
        "cleansesInPerMinute": 48.786127167630056,
        "deathPerMinute": 0.09933774834437087,
        "deathRatio": 17.647058823529413,
        "downPerMinute": 0.16556291390728478,
        "durationInCombat": 1557,
        "evadePerMinute": 28.362235067437382,
        "id": "Karmalee.4721",
        "invulnsPerMinute": 10.90558766859345,
        "opScore": 0.0,
        "profession": "圣言",
        "quicknessPerSecond": 0.34891361592806674,
        "regenerationUptime": 85.7091,
        "resPerMinute": 0.3082851637764933,
        "resistancePerSecond": 0.40549409120102753,
        "ripsInPerMinute": 0.03853564547206166,
        "riteUptime": 22.9297,
        "score": 86.13419105449859,
        "stabilityPerSecond": 1.008481053307643,
        "surviveRatio": 85.9271523178808
    },
    {
        "appliedCrowdControlPerMinute": 0.7838014369693012,
        "blockPerMinute": 11.247550620509472,
        "cleansesInPerMinute": 85.63030698889615,
        "deathPerMinute": 0.16556291390728478,
        "deathRatio": 29.41176470588235,
        "downPerMinute": 0.2980132450331126,
        "durationInCombat": 1531,
        "evadePerMinute": 40.56172436316133,
        "id": "兜里有糖.2715",
        "invulnsPerMinute": 30.176355323318095,
        "opScore": 0.0,
        "profession": "圣言",
        "quicknessPerSecond": 0.5455015676028738,
        "regenerationUptime": 82.746,
        "resPerMinute": 0.43109079033311565,
        "resistancePerSecond": 0.5036407576747224,
        "ripsInPerMinute": 0.15676028739386022,
        "riteUptime": 28.4949,
        "score": 85.23492415034107,
        "stabilityPerSecond": 1.183269105160026,
        "surviveRatio": 84.49227373068433
    },
    {
        "appliedCrowdControlPerMinute": 0.8083282302510717,
        "blockPerMinute": 7.605633802816902,
        "cleansesInPerMinute": 68.63441518677281,
        "deathPerMinute": 0.13245033112582782,
        "deathRatio": 23.529411764705884,
        "downPerMinute": 0.3642384105960265,
        "durationInCombat": 1633,
        "evadePerMinute": 35.97060624617269,
        "id": "葱娘萌杀萝莉控.1487",
        "invulnsPerMinute": 25.425597060624618,
        "opScore": 0.0,
        "profession": "圣言",
        "quicknessPerSecond": 0.43798334353949786,
        "regenerationUptime": 85.6431,
        "resPerMinute": 1.2859767299448868,
        "resistancePerSecond": 0.3827352725045927,
        "ripsInPerMinute": 0.18371096142069812,
        "riteUptime": 27.3953,
        "score": 84.78303629508116,
        "stabilityPerSecond": 1.0968089406001227,
        "surviveRatio": 90.12141280353201
    },
    {
        "appliedCrowdControlPerMinute": 3.7610881135422827,
        "blockPerMinute": 85.7244234180958,
        "cleansesInPerMinute": 44.4234180958013,
        "deathPerMinute": 0.06622516556291391,
        "deathRatio": 11.764705882352942,
        "downPerMinute": 0.09933774834437087,
        "durationInCombat": 1691,
        "evadePerMinute": 254.0508574807806,
        "id": "但为君故.3846",
        "invulnsPerMinute": 17.953873447664105,
        "opScore": 0.0,
        "profession": "裁决",
        "quicknessPerSecond": 0.0,
        "regenerationUptime": 89.2496,
        "resPerMinute": 0.0,
        "resistancePerSecond": 0.2789318154937907,
        "ripsInPerMinute": 25.156712004730927,
        "riteUptime": 43.425,
        "score": 95.29059513226105,
        "stabilityPerSecond": 0.9932755765819042,
        "surviveRatio": 93.32229580573951
    },
    {
        "appliedCrowdControlPerMinute": 3.2040686586141134,
        "blockPerMinute": 45.31468531468532,
        "cleansesInPerMinute": 35.70247933884298,
        "deathPerMinute": 0.13245033112582782,
        "deathRatio": 23.529411764705884,
        "downPerMinute": 0.16556291390728478,
        "durationInCombat": 1573,
        "evadePerMinute": 271.46853146853147,
        "id": "地瓜丶.7925",
        "invulnsPerMinute": 13.54100445009536,
        "opScore": 0.0,
        "profession": "裁决",
        "quicknessPerSecond": 0.0,
        "regenerationUptime": 88.1913,
        "resPerMinute": 0.07628734901462175,
        "resistancePerSecond": 0.42798092816274635,
        "ripsInPerMinute": 22.466624284806105,
        "riteUptime": 43.384,
        "score": 92.40227683213837,
        "stabilityPerSecond": 1.044928798474253,
        "surviveRatio": 86.81015452538631
    },
    {
        "appliedCrowdControlPerMinute": 2.7857142857142856,
        "blockPerMinute": 85.28571428571429,
        "cleansesInPerMinute": 32.785714285714285,
        "deathPerMinute": 0.09933774834437087,
        "deathRatio": 17.647058823529413,
        "downPerMinute": 0.09933774834437087,
        "durationInCombat": 1680,
        "evadePerMinute": 113.85714285714286,
        "id": "咸宁七.5429",
        "invulnsPerMinute": 18.392857142857142,
        "opScore": 0.0,
        "profession": "裁决",
        "quicknessPerSecond": 0.0,
        "regenerationUptime": 83.6826,
        "resPerMinute": 0.07142857142857142,
        "resistancePerSecond": 0.34983928571428563,
        "ripsInPerMinute": 21.964285714285715,
        "riteUptime": 37.3672,
        "score": 92.27940078051087,
        "stabilityPerSecond": 0.37201071428571425,
        "surviveRatio": 92.71523178807946
    },
    {
        "appliedCrowdControlPerMinute": 1.1970074812967582,
        "blockPerMinute": 42.38154613466334,
        "cleansesInPerMinute": 34.22693266832918,
        "deathPerMinute": 0.09933774834437087,
        "deathRatio": 17.647058823529413,
        "downPerMinute": 0.13245033112582782,
        "durationInCombat": 1604,
        "evadePerMinute": 195.0374064837905,
        "id": "寒鸦少年.3216",
        "invulnsPerMinute": 6.508728179551122,
        "opScore": 0.0,
        "profession": "裁决",
        "quicknessPerSecond": 0.0,
        "regenerationUptime": 82.7966,
        "resPerMinute": 0.03740648379052369,
        "resistancePerSecond": 0.35704127182044887,
        "ripsInPerMinute": 22.51870324189526,
        "riteUptime": 34.6634,
        "score": 90.2813645960784,
        "stabilityPerSecond": 0.8074613466334164,
        "surviveRatio": 88.52097130242825
    },
    {
        "appliedCrowdControlPerMinute": 2.5377643504531724,
        "blockPerMinute": 64.38670694864048,
        "cleansesInPerMinute": 40.82175226586103,
        "deathPerMinute": 0.09933774834437087,
        "deathRatio": 17.647058823529413,
        "downPerMinute": 0.26490066225165565,
        "durationInCombat": 1655,
        "evadePerMinute": 156.76132930513594,
        "id": "季总丶.9084",
        "invulnsPerMinute": 14.030211480362539,
        "opScore": 0.0,
        "profession": "裁决",
        "quicknessPerSecond": 0.0,
        "regenerationUptime": 83.6967,
        "resPerMinute": 0.1812688821752266,
        "resistancePerSecond": 0.3088642900302115,
        "ripsInPerMinute": 25.01510574018127,
        "riteUptime": 33.7274,
        "score": 88.67677350993378,
        "stabilityPerSecond": 1.0938761329305138,
        "surviveRatio": 91.3355408388521
    },
    {
        "appliedCrowdControlPerMinute": 1.9354838709677418,
        "blockPerMinute": 64.85630498533725,
        "cleansesInPerMinute": 39.941348973607035,
        "deathPerMinute": 0.06622516556291391,
        "deathRatio": 11.764705882352942,
        "downPerMinute": 0.09933774834437087,
        "durationInCombat": 1705,
        "evadePerMinute": 266.0058651026393,
        "id": "九成宫.3512",
        "invulnsPerMinute": 26.709677419354836,
        "opScore": 0.0,
        "profession": "裁决",
        "quicknessPerSecond": 0.0,
        "regenerationUptime": 88.3738,
        "resPerMinute": 0.03519061583577712,
        "resistancePerSecond": 0.2691155425219941,
        "ripsInPerMinute": 14.674486803519061,
        "riteUptime": 29.121,
        "score": 88.35118954953755,
        "stabilityPerSecond": 0.7880005865102637,
        "surviveRatio": 94.09492273730685
    },
    {
        "appliedCrowdControlPerMinute": 1.7973231357552581,
        "blockPerMinute": 89.63671128107075,
        "cleansesInPerMinute": 41.30019120458891,
        "deathPerMinute": 0.09933774834437087,
        "deathRatio": 17.647058823529413,
        "downPerMinute": 0.13245033112582782,
        "durationInCombat": 1569,
        "evadePerMinute": 216.94072657743786,
        "id": "cczzyy.7649",
        "invulnsPerMinute": 24.74187380497132,
        "opScore": 0.0,
        "profession": "裁决",
        "quicknessPerSecond": 0.0,
        "regenerationUptime": 83.4647,
        "resPerMinute": 0.19120458891013387,
        "resistancePerSecond": 0.23288687061822813,
        "ripsInPerMinute": 18.47036328871893,
        "riteUptime": 26.8583,
        "score": 82.72552259520482,
        "stabilityPerSecond": 0.34513193116634805,
        "surviveRatio": 86.58940397350993
    },
    {
        "appliedCrowdControlPerMinute": 1.750759878419453,
        "blockPerMinute": 52.12158054711246,
        "cleansesInPerMinute": 56.680851063829785,
        "deathPerMinute": 0.09933774834437087,
        "deathRatio": 17.647058823529413,
        "downPerMinute": 0.26490066225165565,
        "durationInCombat": 1645,
        "evadePerMinute": 194.29787234042553,
        "id": "raner.6405",
        "invulnsPerMinute": 16.996960486322187,
        "opScore": 0.0,
        "profession": "裁决",
        "quicknessPerSecond": 0.0,
        "regenerationUptime": 85.8503,
        "resPerMinute": 0.2917933130699088,
        "resistancePerSecond": 0.3371842553191489,
        "ripsInPerMinute": 10.541033434650455,
        "riteUptime": 27.907,
        "score": 81.83593703576965,
        "stabilityPerSecond": 1.0227665653495441,
        "surviveRatio": 90.78366445916114
    },
    {
        "appliedCrowdControlPerMinute": 2.5796886582653817,
        "blockPerMinute": 63.46923647146034,
        "cleansesInPerMinute": 41.85322461082283,
        "deathPerMinute": 0.26490066225165565,
        "deathRatio": 47.05882352941177,
        "downPerMinute": 0.5629139072847682,
        "durationInCombat": 1349,
        "evadePerMinute": 145.0407709414381,
        "id": "伦家锤你小胸胸.2913",
        "invulnsPerMinute": 56.93106004447739,
        "opScore": 0.0,
        "profession": "裁决",
        "quicknessPerSecond": 0.0,
        "regenerationUptime": 73.7189,
        "resPerMinute": 0.0,
        "resistancePerSecond": 0.25860185322461077,
        "ripsInPerMinute": 20.50407709414381,
        "riteUptime": 30.7524,
        "score": 71.26733216919736,
        "stabilityPerSecond": 0.6980422535211268,
        "surviveRatio": 74.44812362030905
    },
    {
        "appliedCrowdControlPerMinute": 1.614802354920101,
        "blockPerMinute": 150.63078216989067,
        "cleansesInPerMinute": 53.03616484440707,
        "deathPerMinute": 0.2980132450331126,
        "deathRatio": 52.94117647058823,
        "downPerMinute": 0.5960264900662252,
        "durationInCombat": 1189,
        "evadePerMinute": 407.0815811606392,
        "id": "追风二狗子.5832",
        "invulnsPerMinute": 66.96383515559293,
        "opScore": 0.0,
        "profession": "裁决",
        "quicknessPerSecond": 0.0,
        "regenerationUptime": 78.8567,
        "resPerMinute": 0.050462573591253154,
        "resistancePerSecond": 0.4333157275021026,
        "ripsInPerMinute": 26.69470142977292,
        "riteUptime": 26.7653,
        "score": 69.4618584317136,
        "stabilityPerSecond": 0.7942910008410431,
        "surviveRatio": 65.61810154525386
    },
    {
        "appliedCrowdControlPerMinute": 0.0,
        "blockPerMinute": 7.165913492575855,
        "cleansesInPerMinute": 132.89864428663654,
        "deathPerMinute": 0.09933774834437087,
        "deathRatio": 17.647058823529413,
        "downPerMinute": 0.13245033112582782,
        "durationInCombat": 1549,
        "evadePerMinute": 43.499031633311816,
        "id": "长期速逝.2587",
        "invulnsPerMinute": 5.074241446094255,
        "opScore": 0.0,
        "profession": "奶德",
        "quicknessPerSecond": 0.18248450613298897,
        "regenerationUptime": 86.244,
        "resPerMinute": 0.19367333763718528,
        "resistancePerSecond": 0.06548043899289865,
        "ripsInPerMinute": 0.38734667527437056,
        "riteUptime": 33.0849,
        "score": 89.15601963639577,
        "stabilityPerSecond": 0.10461394448030988,
        "surviveRatio": 85.48565121412804
    },
    {
        "appliedCrowdControlPerMinute": 0.0,
        "blockPerMinute": 6.72029702970297,
        "cleansesInPerMinute": 128.20544554455446,
        "deathPerMinute": 0.09933774834437087,
        "deathRatio": 17.647058823529413,
        "downPerMinute": 0.09933774834437087,
        "durationInCombat": 1616,
        "evadePerMinute": 28.96039603960396,
        "id": "落英梦.2473",
        "invulnsPerMinute": 6.794554455445544,
        "opScore": 0.0,
        "profession": "奶德",
        "quicknessPerSecond": 0.23043842821782176,
        "regenerationUptime": 84.577,
        "resPerMinute": 0.4084158415841584,
        "resistancePerSecond": 0.04598217821782179,
        "ripsInPerMinute": 0.48267326732673266,
        "riteUptime": 41.2622,
        "score": 89.03341063828238,
        "stabilityPerSecond": 0.004287747524752476,
        "surviveRatio": 89.1832229580574
    },
    {
        "appliedCrowdControlPerMinute": 0.15315890236119975,
        "blockPerMinute": 5.85832801531589,
        "cleansesInPerMinute": 127.31333758774728,
        "deathPerMinute": 0.13245033112582782,
        "deathRatio": 23.529411764705884,
        "downPerMinute": 0.13245033112582782,
        "durationInCombat": 1567,
        "evadePerMinute": 43.03765156349713,
        "id": "ZanTtttt.5938",
        "invulnsPerMinute": 13.937460114869177,
        "opScore": 0.0,
        "profession": "奶德",
        "quicknessPerSecond": 0.2754610082961072,
        "regenerationUptime": 86.0249,
        "resPerMinute": 0.03828972559029994,
        "resistancePerSecond": 0.08256107211231653,
        "ripsInPerMinute": 0.38289725590299933,
        "riteUptime": 37.0888,
        "score": 88.11607971887527,
        "stabilityPerSecond": 0.027285896617740904,
        "surviveRatio": 86.47902869757175
    },
    {
        "appliedCrowdControlPerMinute": 0.15364916773367476,
        "blockPerMinute": 7.067861715749039,
        "cleansesInPerMinute": 107.78489116517285,
        "deathPerMinute": 0.16556291390728478,
        "deathRatio": 29.41176470588235,
        "downPerMinute": 0.2980132450331126,
        "durationInCombat": 1562,
        "evadePerMinute": 35.723431498079385,
        "id": "seyacaga.6418",
        "invulnsPerMinute": 18.16901408450704,
        "opScore": 0.0,
        "profession": "奶德",
        "quicknessPerSecond": 0.16897061459667093,
        "regenerationUptime": 84.1764,
        "resPerMinute": 0.5377720870678617,
        "resistancePerSecond": 0.05002746478873239,
        "ripsInPerMinute": 0.34571062740076824,
        "riteUptime": 29.4957,
        "score": 77.06277199978518,
        "stabilityPerSecond": 0.0081101152368758,
        "surviveRatio": 86.20309050772627
    },
    {
        "appliedCrowdControlPerMinute": 0.15925680159256803,
        "blockPerMinute": 8.122096881220969,
        "cleansesInPerMinute": 111.32050431320503,
        "deathPerMinute": 0.2317880794701987,
        "deathRatio": 41.1764705882353,
        "downPerMinute": 0.43046357615894043,
        "durationInCombat": 1507,
        "evadePerMinute": 43.039150630391504,
        "id": "打折你小牛子.2690",
        "invulnsPerMinute": 27.949568679495687,
        "opScore": 0.0,
        "profession": "奶德",
        "quicknessPerSecond": 0.21151944260119446,
        "regenerationUptime": 83.4519,
        "resPerMinute": 0.23888520238885202,
        "resistancePerSecond": 0.05714976775049768,
        "ripsInPerMinute": 0.35832780358327804,
        "riteUptime": 38.8749,
        "score": 72.40144062760831,
        "stabilityPerSecond": 0.02647644326476443,
        "surviveRatio": 83.16777041942605
    },
    {
        "appliedCrowdControlPerMinute": 0.0,
        "blockPerMinute": 7.886792452830188,
        "cleansesInPerMinute": 98.0,
        "deathPerMinute": 0.13245033112582782,
        "deathRatio": 23.529411764705884,
        "downPerMinute": 0.43046357615894043,
        "durationInCombat": 1590,
        "evadePerMinute": 24.0,
        "id": "李献计.6703",
        "invulnsPerMinute": 26.22641509433962,
        "opScore": 0.0,
        "profession": "奶德",
        "quicknessPerSecond": 0.1797133962264151,
        "regenerationUptime": 86.1201,
        "resPerMinute": 0.4528301886792453,
        "resistancePerSecond": 0.05584094339622641,
        "ripsInPerMinute": 0.41509433962264153,
        "riteUptime": 27.5516,
        "score": 70.56837387188138,
        "stabilityPerSecond": 0.05490943396226415,
        "surviveRatio": 87.74834437086092
    },
    {
        "appliedCrowdControlPerMinute": 6.216216216216217,
        "blockPerMinute": 8.146718146718147,
        "cleansesInPerMinute": 8.223938223938225,
        "deathPerMinute": 0.13245033112582782,
        "deathRatio": 23.529411764705884,
        "downPerMinute": 0.2317880794701987,
        "durationInCombat": 1554,
        "evadePerMinute": 34.440154440154444,
        "id": "东悦丶.1836",
        "invulnsPerMinute": 13.8996138996139,
        "opScore": 0.0,
        "profession": "先驱",
        "quicknessPerSecond": 0.5300859073359073,
        "regenerationUptime": 82.3801,
        "resPerMinute": 1.2741312741312742,
        "resistancePerSecond": 0.31006608751608755,
        "ripsInPerMinute": 66.13899613899615,
        "riteUptime": 37.0883,
        "score": 80.5264610554263,
        "stabilityPerSecond": 0.5701795366795367,
        "surviveRatio": 85.76158940397352
    },
    {
        "appliedCrowdControlPerMinute": 6.743119266055046,
        "blockPerMinute": 6.330275229357798,
        "cleansesInPerMinute": 6.43348623853211,
        "deathPerMinute": 0.033112582781456956,
        "deathRatio": 5.882352941176471,
        "downPerMinute": 0.06622516556291391,
        "durationInCombat": 1744,
        "evadePerMinute": 32.44266055045872,
        "id": "风花雪月伤孤独.3159",
        "invulnsPerMinute": 5.401376146788991,
        "opScore": 0.0,
        "profession": "先驱",
        "quicknessPerSecond": 0.4601378440366972,
        "regenerationUptime": 87.0132,
        "resPerMinute": 0.20642201834862386,
        "resistancePerSecond": 0.22674787844036695,
        "ripsInPerMinute": 61.7545871559633,
        "riteUptime": 33.3544,
        "score": 78.83941969629078,
        "stabilityPerSecond": 0.6079959862385321,
        "surviveRatio": 96.24724061810154
    },
    {
        "appliedCrowdControlPerMinute": 4.972776769509982,
        "blockPerMinute": 7.404718693284936,
        "cleansesInPerMinute": 7.840290381125227,
        "deathPerMinute": 0.09933774834437087,
        "deathRatio": 17.647058823529413,
        "downPerMinute": 0.09933774834437087,
        "durationInCombat": 1653,
        "evadePerMinute": 34.08348457350272,
        "id": "上弦月.8934",
        "invulnsPerMinute": 3.629764065335753,
        "opScore": 0.0,
        "profession": "先驱",
        "quicknessPerSecond": 0.4171174833635813,
        "regenerationUptime": 86.4936,
        "resPerMinute": 0.8711433756805808,
        "resistancePerSecond": 0.2483646702964307,
        "ripsInPerMinute": 57.277676950998185,
        "riteUptime": 28.0273,
        "score": 78.17021299423483,
        "stabilityPerSecond": 0.6800465819721716,
        "surviveRatio": 91.2251655629139
    },
    {
        "appliedCrowdControlPerMinute": 5.129310344827586,
        "blockPerMinute": 9.267241379310345,
        "cleansesInPerMinute": 49.56896551724138,
        "deathPerMinute": 0.2317880794701987,
        "deathRatio": 41.1764705882353,
        "downPerMinute": 0.43046357615894043,
        "durationInCombat": 1392,
        "evadePerMinute": 53.577586206896555,
        "id": "潇轻zZ.4132",
        "invulnsPerMinute": 25.689655172413794,
        "opScore": 0.0,
        "profession": "先驱",
        "quicknessPerSecond": 0.45492097701149425,
        "regenerationUptime": 85.7432,
        "resPerMinute": 0.3017241379310345,
        "resistancePerSecond": 0.3140174568965517,
        "ripsInPerMinute": 66.5948275862069,
        "riteUptime": 32.0719,
        "score": 67.71163475536652,
        "stabilityPerSecond": 0.6165725574712645,
        "surviveRatio": 76.82119205298014
    },
    {
        "deathPerMinute": 0.06622516556291391,
        "deathRatio": 11.764705882352942,
        "dmgPerSecond": 5123.861479028697,
        "downPerMinute": 0.16556291390728478,
        "downsPerMinute": 0.9952606635071091,
        "durationInCombat": 1688,
        "id": "Karen.2765",
        "opScore": 0.0,
        "profession": "全息",
        "score": 93.37748344370861,
        "surviveRatio": 93.15673289183223
    },
    {
        "deathPerMinute": 0.19867549668874174,
        "deathRatio": 35.294117647058826,
        "dmgPerSecond": 4159.685982339955,
        "downPerMinute": 0.2317880794701987,
        "downsPerMinute": 0.6473364801078895,
        "durationInCombat": 1483,
        "id": "李知花.2590",
        "opScore": 0.0,
        "profession": "全息",
        "score": 80.64470860927152,
        "surviveRatio": 81.84326710816777
    },
    {
        "deathPerMinute": 0.33112582781456956,
        "deathRatio": 58.8235294117647,
        "dmgPerSecond": 4192.037527593819,
        "downPerMinute": 0.3973509933774835,
        "downsPerMinute": 1.489191353082466,
        "durationInCombat": 1249,
        "id": "请别叫我麦乐基.7094",
        "opScore": 0.0,
        "profession": "全息",
        "score": 74.41041059602648,
        "surviveRatio": 68.92935982339957
    },
    {
        "deathPerMinute": 0.0,
        "deathRatio": 0.0,
        "dmgPerSecond": 4799.01766004415,
        "downPerMinute": 0.0,
        "downsPerMinute": 0.47323943661971835,
        "durationInCombat": 1775,
        "id": "卿晓之.4786",
        "opScore": 0.0,
        "profession": "猎龙",
        "score": 97.5882119205298,
        "surviveRatio": 97.95805739514348
    },
    {
        "deathPerMinute": 0.16556291390728478,
        "deathRatio": 29.41176470588235,
        "dmgPerSecond": 4887.2522075055185,
        "downPerMinute": 0.19867549668874174,
        "downsPerMinute": 0.54510058403634,
        "durationInCombat": 1541,
        "id": "香蕉君.2615",
        "opScore": 0.0,
        "profession": "猎龙",
        "score": 90.70000662251655,
        "surviveRatio": 85.04415011037527
    },
    {
        "deathPerMinute": 0.09933774834437087,
        "deathRatio": 17.647058823529413,
        "dmgPerSecond": 4406.7146799117,
        "downPerMinute": 0.13245033112582782,
        "downsPerMinute": 0.4893350062735257,
        "durationInCombat": 1594,
        "id": "Hii.1629",
        "opScore": 0.0,
        "profession": "猎龙",
        "score": 87.58256291390728,
        "surviveRatio": 87.96909492273731
    },
    {
        "deathPerMinute": 0.26490066225165565,
        "deathRatio": 47.05882352941177,
        "dmgPerSecond": 4315.171633554084,
        "downPerMinute": 0.3642384105960265,
        "downsPerMinute": 0.45112781954887216,
        "durationInCombat": 1330,
        "id": "MADAO战士.6038",
        "opScore": 0.0,
        "profession": "猎龙",
        "score": 77.21252317880794,
        "surviveRatio": 73.39955849889624
    },
    {
        "deathPerMinute": 0.19867549668874174,
        "deathRatio": 35.294117647058826,
        "dmgPerSecond": 4192.195364238411,
        "downPerMinute": 0.33112582781456956,
        "downsPerMinute": 0.6382978723404256,
        "durationInCombat": 1410,
        "id": "我真是服了.5167",
        "opScore": 0.0,
        "profession": "猎龙",
        "score": 77.06131125827815,
        "surviveRatio": 77.81456953642385
    },
    {
        "deathPerMinute": 0.33112582781456956,
        "deathRatio": 58.8235294117647,
        "dmgPerSecond": 3994.4646799117,
        "downPerMinute": 0.33112582781456956,
        "downsPerMinute": 0.8411214953271029,
        "durationInCombat": 1284,
        "id": "找到胖丁了吗.5720",
        "opScore": 0.0,
        "profession": "猎龙",
        "score": 74.68854304635761,
        "surviveRatio": 70.86092715231788
    },
    {
        "deathPerMinute": 0.2980132450331126,
        "deathRatio": 52.94117647058823,
        "dmgPerSecond": 3841.7130242825606,
        "downPerMinute": 0.3642384105960265,
        "downsPerMinute": 0.47132757266300085,
        "durationInCombat": 1273,
        "id": "Muggle.4716",
        "opScore": 0.0,
        "profession": "猎龙",
        "score": 71.53101986754966,
        "surviveRatio": 70.25386313465783
    },
    {
        "deathPerMinute": 0.2980132450331126,
        "deathRatio": 52.94117647058823,
        "dmgPerSecond": 3827.8118101545256,
        "downPerMinute": 0.4635761589403974,
        "downsPerMinute": 0.5081157374735357,
        "durationInCombat": 1417,
        "id": "吃肉的流氓兔.6078",
        "opScore": 0.0,
        "profession": "猎龙",
        "score": 67.39069536423841,
        "surviveRatio": 78.2008830022075
    },
    {
        "deathPerMinute": 0.33112582781456956,
        "deathRatio": 58.8235294117647,
        "dmgPerSecond": 3786.0397350993376,
        "downPerMinute": 0.4635761589403974,
        "downsPerMinute": 0.5347593582887701,
        "durationInCombat": 1122,
        "id": "Jason.6714",
        "opScore": 0.0,
        "profession": "猎龙",
        "score": 66.88943046357615,
        "surviveRatio": 61.920529801324506
    },
    {
        "deathPerMinute": 0.33112582781456956,
        "deathRatio": 58.8235294117647,
        "dmgPerSecond": 3603.437086092715,
        "downPerMinute": 0.43046357615894043,
        "downsPerMinute": 0.5012531328320802,
        "durationInCombat": 1197,
        "id": "方砖叔.5287",
        "opScore": 0.0,
        "profession": "猎龙",
        "score": 66.02270198675497,
        "surviveRatio": 66.05960264900662
    }
]